dominant_color_recognizer/__init__.py
dominant_color_recognizer/main.py
dominant_color_recognizer/test.jpg
dominantcolorrecognizer-1.0.0.dist-info/WHEEL
dominantcolorrecognizer-1.0.0.dist-info/METADATA
dominantcolorrecognizer-1.0.0.dist-info/RECORD
