Metadata-Version: 2.1
Name: dominantcolorrecognizer
Version: 1.0.0
Summary: Python library created to obtain a specific number of dominant colors from an image.
License: Bitapps
Author: Wojciech Batorski
Author-email: wojciech.batorski@bitapps.fi
Requires-Python: >=3.10,<4.0
Classifier: License :: Other/Proprietary License
Classifier: Programming Language :: Python :: 3
Classifier: Programming Language :: Python :: 3.10
Classifier: Programming Language :: Python :: 3.11
Requires-Dist: black (>=22.10.0,<23.0.0)
Requires-Dist: colormap (>=1.0.4,<2.0.0)
Requires-Dist: easydev (>=0.12.0,<0.13.0)
Requires-Dist: extcolors (>=1.0.0,<2.0.0)
Requires-Dist: isort (>=5.10.1,<6.0.0)
Requires-Dist: mypy (>=0.990,<0.991)
